pyle38/__init__.py
pyle38/client.py
pyle38/client_options.py
pyle38/errors.py
pyle38/follower.py
pyle38/leader.py
pyle38/models.py
pyle38/parse_response.py
pyle38/responses.py
pyle38/tile38.py
pyle38/utils.py
pyle38/commands/__init__.py
pyle38/commands/executable.py
pyle38/commands/fset.py
pyle38/commands/get.py
pyle38/commands/intersects.py
pyle38/commands/nearby.py
pyle38/commands/scan.py
pyle38/commands/search.py
pyle38/commands/set.py
pyle38/commands/setchan.py
pyle38/commands/sethook.py
pyle38/commands/whereable.py
pyle38/commands/within.py
pyle38-1.0.0.dist-info/METADATA
pyle38-1.0.0.dist-info/WHEEL
pyle38-1.0.0.dist-info/licenses/LICENSE
pyle38-1.0.0.dist-info/RECORD
