Metadata-Version: 2.4
Name: pyle38
Version: 1.0.0
Summary: python client for Tile38
Project-URL: Homepage, https://iwpnd.github.io/pyle38
Project-URL: Repository, https://github.com/iwpnd/pyle38
Project-URL: Documentation, https://iwpnd.github.io/pyle38
Author-email: Benjamin Ramser <iwpnd@posteo.de>
License-Expression: MIT
License-File: LICENSE
Keywords: async,client,tile38
Classifier: Intended Audience :: Developers
Classifier: Programming Language :: Python
Classifier: Programming Language :: Python :: 3
Classifier: Programming Language :: Python :: 3.10
Classifier: Programming Language :: Python :: 3.11
Classifier: Programming Language :: Python :: 3.12
Classifier: Programming Language :: Python :: 3.13
Classifier: Topic :: Database :: Front-Ends
Classifier: Topic :: Scientific/Engineering :: GIS
Classifier: Topic :: Software Development :: Libraries :: Python Modules
Classifier: Typing :: Typed
Requires-Python: <4.0,>=3.10
Requires-Dist: pydantic>=2.10.5
Requires-Dist: redis>=5.2.1
